meritum/__init__.py
meritum/meritum.py
meritum/assets/meritum_add_goals2.png
meritum/assets/meritum_add_student.png
meritum/assets/meritum_add_tasks.png
meritum/assets/meritum_main.png
meritum/assets/meritum_select_mode.png
meritum-0.3.0.dist-info/licenses/LICENSE
meritum-0.3.0.dist-info/METADATA
meritum-0.3.0.dist-info/WHEEL
meritum-0.3.0.dist-info/entry_points.txt
meritum-0.3.0.dist-info/top_level.txt
meritum-0.3.0.dist-info/RECORD
