Metadata-Version: 2.4
Name: meritum
Version: 0.3.0
Summary: A tool for tracking student progress using Gantt charts and task management
Home-page: https://github.com/maurobedoya/meritum
Author: Mauricio Bedoya
License: MIT
Classifier: Programming Language :: Python :: 3
Classifier: Operating System :: OS Independent
Classifier: Development Status :: 4 - Beta
Classifier: Intended Audience :: Education
Classifier: Topic :: Office/Business :: Scheduling
Requires-Python: >=3.7
License-File: LICENSE
Requires-Dist: customtkinter>=5.2.2
Dynamic: author
Dynamic: classifier
Dynamic: description
Dynamic: description-content-type
Dynamic: home-page
Dynamic: license
Dynamic: license-file
Dynamic: requires-dist
Dynamic: requires-python
Dynamic: summary
